ohio/__init__.py
ohio/baseio.py
ohio/csvio.py
ohio/iterio.py
ohio/pipeio.py
ohio/ext/__init__.py
ohio/ext/numpy.py
ohio/ext/pandas.py
ohio/recipe/__init__.py
ohio/recipe/dbjoin.py
ohio-0.5.0.dist-info/LICENSE
ohio-0.5.0.dist-info/METADATA
ohio-0.5.0.dist-info/WHEEL
ohio-0.5.0.dist-info/top_level.txt
ohio-0.5.0.dist-info/RECORD
