Metadata-Version: 2.1
Name: ohio
Version: 0.5.0
Summary: I/O extras
Home-page: https://github.com/dssg/ohio
Author: Center for Data Science and Public Policy
Author-email: datascifellows@gmail.com
License: UNKNOWN
Platform: UNKNOWN
Classifier: Development Status :: 4 - Beta
Classifier: Intended Audience :: Developers
Classifier: Natural Language :: English
Classifier: Programming Language :: Python :: 3
